LICENSE
MANIFEST.in
README.rst
setup.py
podcats/__init__.py
podcats.egg-info/PKG-INFO
podcats.egg-info/SOURCES.txt
podcats.egg-info/dependency_links.txt
podcats.egg-info/entry_points.txt
podcats.egg-info/requires.txt
podcats.egg-info/top_level.txt
podcats/templates/episode.html
podcats/templates/episode.xml
podcats/templates/feed.html
podcats/templates/feed.xml