Metadata-Version: 1.1
Name: podcats
Version: 0.6.2
Summary: An application that generates RSS feeds for podcast episodes from local audio files and, optionally, exposes both via a built-in web server
Home-page: https://github.com/jakubroztocil/podcats
Author: Jakub Roztocil
Author-email: jakub@subtleapps.com
License: BSD
Download-URL: https://github.com/jakubroztocil/podcats
Platform: UNKNOWN
Classifier: Development Status :: 5 - Production/Stable
Classifier: Programming Language :: Python
Classifier: Programming Language :: Python :: 2.7
Classifier: Programming Language :: Python :: 3.7
Classifier: Environment :: Console
Classifier: Intended Audience :: End Users/Desktop
Classifier: License :: OSI Approved :: BSD License
Classifier: Topic :: Multimedia :: Sound/Audio
